.travis.yml
CHANGELOG.md
LICENSE
MANIFEST.in
README.md
setup.py
argparse2/__init__.py
argparse2/argparse.py
argparse2/test_argparse.py
argparse2.egg-info/PKG-INFO
argparse2.egg-info/SOURCES.txt
argparse2.egg-info/dependency_links.txt
argparse2.egg-info/requires.txt
argparse2.egg-info/top_level.txt
docs/argparse.rst