Metadata-Version: 1.1
Name: argparse2
Version: 0.5.0-alpha
Summary: Fork of Python's argparse to add features and simplify its code
Home-page: https://github.com/cjerdonek/python-argparse
Author: Chris Jerdonek
Author-email: chris.jerdonek@gmail.com
License: Python Software Foundation License
Keywords: argparse argparse2 command line parser parsing
Platform: UNKNOWN
Classifier: Development Status :: 3 - Alpha
Classifier: Intended Audience :: Developers
Classifier: License :: OSI Approved :: Python Software Foundation License
Classifier: Programming Language :: Python :: 3
Classifier: Programming Language :: Python :: 3.4
Classifier: Topic :: Software Development
